snaplogic_common_robot/__init__.py
snaplogic_common_robot/libdocs/common_utilities.html
snaplogic_common_robot/libdocs/index.html
snaplogic_common_robot/libdocs/raw_common_utilities.html
snaplogic_common_robot/libdocs/raw_snaplogic_apis.html
snaplogic_common_robot/libdocs/raw_snaplogic_keywords.html
snaplogic_common_robot/libdocs/robot-doc-styles.css
snaplogic_common_robot/libdocs/snaplogic_apis.html
snaplogic_common_robot/libdocs/snaplogic_keywords.html
snaplogic_common_robot/libraries/__init__.py
snaplogic_common_robot/libraries/utils.py
snaplogic_common_robot/libraries/jms/__init__.py
snaplogic_common_robot/libraries/jms/cleanup_library_definitions.py
snaplogic_common_robot/libraries/jms/cleanup_queue_address_script.py
snaplogic_common_robot/libraries/jms/robot_stomp_wrapper.py
snaplogic_common_robot/libraries/jms/stomp_library_definitions.py
snaplogic_common_robot/snaplogic_apis_keywords/__init__.py
snaplogic_common_robot/snaplogic_apis_keywords/common_utilities.resource
snaplogic_common_robot/snaplogic_apis_keywords/snaplogic_apis.resource
snaplogic_common_robot/snaplogic_apis_keywords/snaplogic_keywords.resource
snaplogic_common_robot/test_data/__init__.py
snaplogic_common_robot/test_data/slim_groundplex.json
snaplogic_common_robot/test_data/triggered_task.json
snaplogic_common_robot-2025.12.16.1.1.dist-info/METADATA
snaplogic_common_robot-2025.12.16.1.1.dist-info/WHEEL
snaplogic_common_robot-2025.12.16.1.1.dist-info/top_level.txt
snaplogic_common_robot-2025.12.16.1.1.dist-info/RECORD
