Metadata-Version: 2.4
Name: snaplogic-common-robot
Version: 2025.12.16.1.1
Summary: Robot Framework library with keywords for SnapLogic API testing and automation
Author-email: SnapLogic <support@snaplogic.com>
License-Expression: Apache-2.0
Project-URL: Documentation, https://github.com/SnapLogic/snaplogic-common-robot#readme
Project-URL: Homepage, https://github.com/SnapLogic/snaplogic-common-robot
Project-URL: Repository, https://github.com/SnapLogic/snaplogic-common-robot
Keywords: robotframework,snaplogic,api,testing,automation,jms,activemq,artemis
Classifier: Framework :: Robot Framework
Classifier: Framework :: Robot Framework :: Library
Classifier: Intended Audience :: Developers
Classifier: Operating System :: OS Independent
Classifier: Programming Language :: Python :: 3
Classifier: Programming Language :: Python :: 3.8
Classifier: Programming Language :: Python :: 3.9
Classifier: Programming Language :: Python :: 3.10
Classifier: Programming Language :: Python :: 3.11
Classifier: Programming Language :: Python :: 3.12
Classifier: Topic :: Software Development :: Testing
Classifier: Topic :: Software Development :: Quality Assurance
Requires-Python: >=3.8
Requires-Dist: robotframework>=3.2
Requires-Dist: robotframework-requests
Requires-Dist: robotframework-docker
Requires-Dist: robotframework-databaselibrary
Requires-Dist: robotframework-jsonlibrary
Requires-Dist: robotframework-robocop
Requires-Dist: robotframework-tidy[generate_config]
Requires-Dist: robotframework-dependencylibrary
Requires-Dist: robotframework-pabot==2.18.0
Requires-Dist: robotframework-csvlibrary
Requires-Dist: stomp-py>=8.0.0
Requires-Dist: requests>=2.25.0
Requires-Dist: jinja2>=2.11.0
Requires-Dist: envyaml
Requires-Dist: deepdiff
Requires-Dist: pyyaml
Requires-Dist: tabulate
Requires-Dist: awscli
Requires-Dist: boto3
Requires-Dist: build
Requires-Dist: twine
Requires-Dist: python-dotenv
Requires-Dist: cookiecutter
Provides-Extra: dev
Requires-Dist: pytest; extra == "dev"
Requires-Dist: pytest-cov; extra == "dev"
Requires-Dist: black; extra == "dev"
Requires-Dist: flake8; extra == "dev"
Requires-Dist: mypy; extra == "dev"
Requires-Dist: pre-commit; extra == "dev"
